evo_prot_grad/__init__.py
evo_prot_grad/common/__init__.py
evo_prot_grad/common/embeddings.py
evo_prot_grad/common/sampler.py
evo_prot_grad/common/tokenizers.py
evo_prot_grad/common/utils.py
evo_prot_grad/common/variant_scoring.py
evo_prot_grad/experts/__init__.py
evo_prot_grad/experts/base_experts.py
evo_prot_grad/experts/bert_expert.py
evo_prot_grad/experts/causallm_expert.py
evo_prot_grad/experts/esm_expert.py
evo_prot_grad/experts/evcouplings_expert.py
evo_prot_grad/experts/onehot_downstream_regression_expert.py
evo_prot_grad/models/__init__.py
evo_prot_grad/models/downstream_cnn.py
evo_prot_grad/models/potts.py
evo_prot_grad-0.2.dist-info/LICENSE
evo_prot_grad-0.2.dist-info/METADATA
evo_prot_grad-0.2.dist-info/WHEEL
evo_prot_grad-0.2.dist-info/top_level.txt
evo_prot_grad-0.2.dist-info/RECORD
