Metadata-Version: 2.1
Name: evo-prot-grad
Version: 0.2
Summary: Directed evolution of proteins with fast gradient-based discrete MCMC.
Home-page: https://github.nrel.gov/NREL/EvoProtGrad/
Author: Patrick Emami
Author-email: Patrick.Emami@nrel.gov
License: BSD 3-Clause
Keywords: protein engineering,directed evolution,huggingface,protein language models,mcmc
Classifier: Development Status :: 3 - Alpha
Classifier: Intended Audience :: Science/Research
Classifier: License :: OSI Approved :: BSD License
Classifier: Natural Language :: English
Classifier: Programming Language :: Python :: 3
Classifier: Topic :: Scientific/Engineering :: Artificial Intelligence
Requires-Python: >=3.8
License-File: LICENSE
Requires-Dist: transformers[torch] (==4.38.0)
